README.md
plib
setup.py
plib/__init__.py
plib/plib.py
plib_these.egg-info/PKG-INFO
plib_these.egg-info/SOURCES.txt
plib_these.egg-info/dependency_links.txt
plib_these.egg-info/requires.txt
plib_these.egg-info/top_level.txt