Metadata-Version: 2.1
Name: plib-these
Version: 0.3.1.post2
Summary: Librairie générale pour la thèse
Home-page: https://github.com/pdelpierre/plib
Author: P. Delpierre / O. Irwin
Author-email: <pauline.delpierre@univ-lille.fr>
License: UNKNOWN
Platform: UNKNOWN
Classifier: Programming Language :: Python :: 3
Classifier: Operating System :: OS Independent
